dlrover/Makefile
dlrover/__init__.py
dlrover/proto/__init__.py
dlrover/proto/brain.proto
dlrover/proto/elastic_training.proto
dlrover/proto/protobuf_3_20_3/__init__.py
dlrover/proto/protobuf_3_20_3/brain_pb2.py
dlrover/proto/protobuf_3_20_3/brain_pb2_grpc.py
dlrover/proto/protobuf_3_20_3/elastic_training_pb2.py
dlrover/proto/protobuf_3_20_3/elastic_training_pb2_grpc.py
dlrover/proto/protobuf_4_25_3/__init__.py
dlrover/proto/protobuf_4_25_3/brain_pb2.py
dlrover/proto/protobuf_4_25_3/brain_pb2_grpc.py
dlrover/proto/protobuf_4_25_3/elastic_training_pb2.py
dlrover/proto/protobuf_4_25_3/elastic_training_pb2_grpc.py
dlrover/python/__init__.py
dlrover/python/brain/__init__.py
dlrover/python/brain/client.py
dlrover/python/common/__init__.py
dlrover/python/common/comm.py
dlrover/python/common/constants.py
dlrover/python/common/enums.py
dlrover/python/common/env_utils.py
dlrover/python/common/error.py
dlrover/python/common/global_context.py
dlrover/python/common/http_server.py
dlrover/python/common/log.py
dlrover/python/common/multi_process.py
dlrover/python/common/node.py
dlrover/python/common/resource.py
dlrover/python/common/serialize.py
dlrover/python/common/singleton.py
dlrover/python/common/storage.py
dlrover/python/common/event/__init__.py
dlrover/python/common/event/context.py
dlrover/python/common/event/dlrover_event.py
dlrover/python/common/event/reporter.py
dlrover/python/common/event/train_event.py
dlrover/python/common/metric/__init__.py
dlrover/python/common/metric/context.py
dlrover/python/common/metric/metric.py
dlrover/python/common/metric/monitor.py
dlrover/python/common/musa_patch/__init__.py
dlrover/python/diagnosis/__init__.py
dlrover/python/diagnosis/common/__init__.py
dlrover/python/diagnosis/common/constants.py
dlrover/python/diagnosis/common/diagnosis_action.py
dlrover/python/diagnosis/common/diagnosis_data.py
dlrover/python/diagnosis/common/diagnosis_manager.py
dlrover/python/diagnosis/common/diagnostician.py
dlrover-0.6.1.dist-info/LICENSE
dlrover-0.6.1.dist-info/METADATA
dlrover-0.6.1.dist-info/WHEEL
dlrover-0.6.1.dist-info/entry_points.txt
dlrover-0.6.1.dist-info/top_level.txt
dlrover-0.6.1.dist-info/RECORD
