Metadata-Version: 2.1
Name: dlrover
Version: 0.6.1
Summary: An Automatic Distributed Deep Learning Framework
Home-page: https://github.com/intelligent-machine-learning/dlrover
Author: Ant Group
License: UNKNOWN
Platform: UNKNOWN
Requires-Python: >=3.8
License-File: LICENSE
Requires-Dist: psutil
Requires-Dist: pynvml
Requires-Dist: deprecated
Requires-Dist: requests
Requires-Dist: packaging
Provides-Extra: k8s
Requires-Dist: kubernetes ; extra == 'k8s'
Requires-Dist: tornado ; extra == 'k8s'
Requires-Dist: grpcio ; extra == 'k8s'
Provides-Extra: ray
Requires-Dist: ray[default] ; extra == 'ray'
Requires-Dist: omegaconf ; extra == 'ray'
Requires-Dist: pydantic ; extra == 'ray'
Provides-Extra: tensorflow
Requires-Dist: tensorflow ; extra == 'tensorflow'
Provides-Extra: torch
Requires-Dist: torch ; extra == 'torch'
